mksms/__init__.py
mksms/client.py
mksms/contact.py
mksms/message.py
mksms-0.1.1.dist-info/LICENSE.txt
mksms-0.1.1.dist-info/METADATA
mksms-0.1.1.dist-info/WHEEL
mksms-0.1.1.dist-info/top_level.txt
mksms-0.1.1.dist-info/RECORD
